redisamp/__init__.py
redisamp/keys.py
redisamp/main.css
redisamp/main.py
redisamp/screens/__init__.py
redisamp/screens/connections.py
redisamp/screens/home.py
redisamp/screens/key_actions.py
redisamp/screens/settings.py
redisamp/widgets/__init__.py
redisamp/widgets/key_view.py
redisamp/widgets/keys/SetKey.py
redisamp/widgets/keys/__init__.py
redisamp/widgets/keys/base.py
redisamp/widgets/keys/hash.py
redisamp/widgets/keys/json.py
redisamp/widgets/keys/list.py
redisamp/widgets/keys/set.py
redisamp/widgets/keys/sorted_set.py
redisamp/widgets/keys/stream.py
redisamp/widgets/keys/string.py
redisamp/widgets/keys_list.py
redisamp-0.1.1.dist-info/LICENSE
redisamp-0.1.1.dist-info/METADATA
redisamp-0.1.1.dist-info/WHEEL
redisamp-0.1.1.dist-info/entry_points.txt
redisamp-0.1.1.dist-info/RECORD
